telegramfeedbackbot/__init__.py
telegramfeedbackbot/telegram_feedback_bot.py
telegram_feedback_bot-0.0.0.dist-info/LICENSE
telegram_feedback_bot-0.0.0.dist-info/METADATA
telegram_feedback_bot-0.0.0.dist-info/WHEEL
telegram_feedback_bot-0.0.0.dist-info/entry_points.txt
telegram_feedback_bot-0.0.0.dist-info/top_level.txt
telegram_feedback_bot-0.0.0.dist-info/RECORD
